hyrax/__init__.py
hyrax/load_balancer.py
hyrax/monitor.py
hyrax/orchestrator.py
hyrax/resource_manager.py
hyrax/worker.py
hyrax_lib-0.2.1.dist-info/licenses/LICENSE
hyrax_lib-0.2.1.dist-info/METADATA
hyrax_lib-0.2.1.dist-info/WHEEL
hyrax_lib-0.2.1.dist-info/top_level.txt
hyrax_lib-0.2.1.dist-info/RECORD
