Metadata-Version: 2.4
Name: hyrax-lib
Version: 0.2.1
Summary: Lightweight distributed training for multi-dataset workflows on local hardware
Author-email: Baljinder Hothi <baljinderh.cs@gmail.com>
Project-URL: Homepage, https://github.com/BaljinderHothi/hyrax-lib
Project-URL: Documentation, https://github.com/BaljinderHothi/hyrax-lib/blob/main/docs/quickstart.md
Project-URL: Bug Tracker, https://github.com/BaljinderHothi/hyrax-lib/issues
Project-URL: Source, https://github.com/BaljinderHothi/hyrax-lib
Keywords: machine-learning,distributed-training,pytorch,gpu,multi-gpu
Classifier: Development Status :: 4 - Beta
Classifier: Intended Audience :: Developers
Classifier: Intended Audience :: Science/Research
Classifier: Programming Language :: Python :: 3
Classifier: Programming Language :: Python :: 3.8
Classifier: Programming Language :: Python :: 3.9
Classifier: Programming Language :: Python :: 3.10
Classifier: Programming Language :: Python :: 3.11
Classifier: Programming Language :: Python :: 3.12
Classifier: License :: OSI Approved :: MIT License
Classifier: Operating System :: OS Independent
Classifier: Topic :: Scientific/Engineering :: Artificial Intelligence
Classifier: Topic :: System :: Distributed Computing
Requires-Python: >=3.8
License-File: LICENSE
Requires-Dist: torch>=2.0.0
Requires-Dist: psutil>=5.9.0
Requires-Dist: tensorboard>=2.11.0
Provides-Extra: dev
Requires-Dist: pytest>=7.0.0; extra == "dev"
Requires-Dist: pytest-cov>=4.0.0; extra == "dev"
Requires-Dist: black>=23.0.0; extra == "dev"
Dynamic: license-file
